CHANGELOG.rst
LICENSE.txt
MANIFEST.in
README.rst
TODO.txt
VERSION.txt
setup.cfg
setup.py
genemail/__init__.py
genemail/cli.py
genemail/email.py
genemail/idict.py
genemail/manager.py
genemail/sender.py
genemail/test.py
genemail/test_testing.py
genemail/testing.py
genemail/util.py
genemail.egg-info/PKG-INFO
genemail.egg-info/SOURCES.txt
genemail.egg-info/dependency_links.txt
genemail.egg-info/entry_points.txt
genemail.egg-info/requires.txt
genemail.egg-info/top_level.txt
genemail.egg-info/zip-safe
genemail/modifier/__init__.py
genemail/modifier/base.py
genemail/modifier/bcc.py
genemail/modifier/dkim.py
genemail/modifier/pgp.py
genemail/modifier/test_bcc.py
genemail/modifier/test_dkim.py
genemail/modifier/test_pgp.py
genemail/test_data/gpg-receiver/pubring.gpg
genemail/test_data/gpg-receiver/random_seed
genemail/test_data/gpg-receiver/secring.gpg
genemail/test_data/gpg-receiver/trustdb.gpg
genemail/test_data/gpg-sender/pubring.gpg
genemail/test_data/gpg-sender/pubring.gpg~
genemail/test_data/gpg-sender/random_seed
genemail/test_data/gpg-sender/secring.gpg
genemail/test_data/gpg-sender/trustdb.gpg
genemail/test_data/templates/email/invite.html
genemail/test_data/templates/email/invite.spec
genemail/test_data/templates/email/invite.text
genemail/test_data/templates/email/logo.png
genemail/test_data/templates/email/sig.png